<permissionsList vocabulary="webern">
    <permissions id="awg-res-default">
        <allow group="UnknownUser">V</allow>
        <allow group="KnownUser">V</allow>
        <allow group="Creator">D</allow>
        <allow group="ProjectMember">D</allow>
        <allow group="ProjectAdmin">CR</allow>
    </permissions>
    <permissions id="awg-res-internal">
        <allow group="Creator">D</allow>
        <allow group="ProjectMember">D</allow>
        <allow group="ProjectAdmin">CR</allow>
    </permissions>
    <permissions id="awg-prop-default">
        <allow group="UnknownUser">V</allow>
        <allow group="KnownUser">V</allow>
        <allow group="Creator">D</allow>
        <allow group="ProjectMember">D</allow>
        <allow group="ProjectAdmin">CR</allow>
    </permissions>
    <permissions id="awg-prop-internal">
        <allow group="Creator">D</allow>
        <allow group="ProjectMember">D</allow>
        <allow group="ProjectAdmin">CR</allow>
    </permissions>
</permissionsList>